{
  "phase_1": {
    "title": "Bienvenue !",
    "choices": {
      "A": {
        "action": "Avancer.",
        "path" : "/game/2"
      }
    }
  },
  "phase_2": {
    "title": "Où aller ?",
    "choices": {
      "A": {
        "action": "A gauche.",
        "path": "/game/3"
      },
      "B": {
        "action": "A droite.",
        "path": "/game/4"
      }
    }
  },
  "phase_3": {
    "title": "Chemin Tranquille",
    "choices": {
      "A": {
        "action": "Avancer.",
        "path": "/game/5"
      }
    }
  },
  "phase_4": {
    "title": "Chemin Dangereux",
    "choices": {
      "A": {
        "action": "Revenir.",
        "path": "/game/2"
      },
      "B": {
        "action": "Avancer.",
        "path": "/game/6"
      }
    }
  },
  "phase_5": {
    "title": "Arrivée",
    "choices": {
      "A": {
        "action": "Continuer.",
        "path": "/win"
      }
    }
  },
  "phase_6": {
    "title": "Piège Mortel",
    "choices": {
      "A": {
        "action": "Continuer.",
        "path": "/lose"
      }
    }
  }
}